gys/Api_Allocate.py
gys/Api_Audit.py
gys/Api_BatchSave.py
gys/Api_BatchSaveQuery.py
gys/Api_Delete.py
gys/Api_ExecuteBillQuery.py
gys/Api_ExecuteOperation.py
gys/Api_GetDataCenters.py
gys/Api_Save.py
gys/Api_Submit.py
gys/Api_UnAudit.py
gys/Api_View.py
gys/__init__.py
gys-1.2.0.dist-info/METADATA
gys-1.2.0.dist-info/WHEEL
gys-1.2.0.dist-info/top_level.txt
gys-1.2.0.dist-info/RECORD
